referbook/LSTMNER.py
referbook/RNNSTT.py
referbook/__init__.py
referbook/bertqa.py
referbook/bertsum.py
referbook/cosinesim.py
referbook/finespee.py
referbook/multi.py
referbook/pcamulti.py
referbook/quan.py
referbook/rnlsgru.py
referbook/sentiment_code.py
referbook/storyneo.py
referbook-0.1.dist-info/METADATA
referbook-0.1.dist-info/WHEEL
referbook-0.1.dist-info/top_level.txt
referbook-0.1.dist-info/RECORD
