Metadata-Version: 2.1
Name: referbook
Version: 0.1
Summary: A reference book with useful Python code examples
Author: ANOS
Classifier: Programming Language :: Python :: 3
Requires-Python: >=3.6
